PythonWalker/__init__.py
PythonWalker/player.py
PythonWalker/world.py
PythonWalker/world_pb2.py
pythonwalker-0.3.1.dist-info/licenses/LICENSE
pythonwalker-0.3.1.dist-info/METADATA
pythonwalker-0.3.1.dist-info/WHEEL
pythonwalker-0.3.1.dist-info/top_level.txt
pythonwalker-0.3.1.dist-info/RECORD
