Metadata-Version: 2.4
Name: PythonWalker
Version: 0.3.1
Summary: A Python based bot library for PixelWalker
Home-page: https://github.com/Tycho10101/PythonWalker
Author: Tycho10101
Author-email: supallawma@gmail.com
Classifier: Programming Language :: Python :: 3
Classifier: License :: OSI Approved :: MIT License
Classifier: Operating System :: OS Independent
Requires-Python: >=3.10
License-File: LICENSE
Requires-Dist: requests>=2.32.3
Requires-Dist: websockets>=13.1
Requires-Dist: protobuf
Requires-Dist: binreader
Dynamic: author
Dynamic: author-email
Dynamic: classifier
Dynamic: description
Dynamic: description-content-type
Dynamic: home-page
Dynamic: license-file
Dynamic: requires-dist
Dynamic: requires-python
Dynamic: summary
